{"БРУСКЕТИ":["Брускета з прошуто","Брускета з лососем (1шт)","Брускета з тушеним м҆ясом (1шт)"],"СКОВОРІДКИ":["Сковорідка з ковбаскою та тушеною капустою (260г)","Сковорідка з курячим філе та кукурудзою (320г)","Сковорідка з м҆'ясом в соусі Барбекю (320г)","Сковорідка з мисливськими ковбасками (320г)","Овочі гриль","Куряча грудка запечена з овочами (320г)"],"ГРИЛЬ":["Пепер стейк (250г)","Маленька ципа гриль (300г)","Курячий стейк (300г)","Ребра свинячі (400г)","Свинячий стейк з ошийка (350г)","Стейк із лосося (250г)","Стейк Філе міньйон (220г)","Тонкий стейк з ошийка (270г)"],"ХОЛОДНІ ЗАКУСКИ":["Асорті сала власного засолу (280г)","Карпачо з лосося (150г)","Норвезький оселедець з маринованою цибулею (500г)","Сирне плато (300г)","Квашенина","Паштет з курячого м'яса (180г)","Печінковий паштет (200г)","Торт печінковий (115г)"],"СТРАВИ НА КОМПАНІЮ":["Дошка снеків (300г)","Хлібна корзина","Дошка фрі мала (500г)","Дошка фрі велика (600г)","М'ясна дошка (900г)","Ковбасний сет (1000г)","М'ясна сковорідка (500г)","Таріль ДаБлін (1000г)"],"ДОМАШНЯ СТОРІНКА":["Вареники з картоплею (300г)","Вареники з картоплею та сиром (300г)","Дерун Пабний (420г)","Пельмені (300г)","Дерун м'ясний (420г)","Вареники чорні з м'ясом (300г)"],"ПЕРШІ СТРАВИ":["Бограч з трьох видів м'яса (300г)","Борщ з грінками чорного хліба і салом (300г)","Солянка з часниковими грінками (300г)","Сирний крем-суп з грінками (220г)"],"САЛАТИ":["Салат Грецький (220г)","Салат з печеним лососем (180г)","Салат з теплою телятиною (240г)","Салат Пабний (270г)","Салат з прошуто (170г)","Салат Цезар з куркою (200г)","Салат Вітамінний (240г)","Кобб салат (250г)"],"ПАСТА":["Паста Вітелло з телятиною та томатами гриль (350г)","Паста Мак енд Чіз","Паста з лососем під вершково-устричним соусом (350г)","Паста з курячими биточками (350г)"],"ГАРНІРИ":["Картопля по-селянськи (180г)","Картопля фрі з часниковим соусом (180г)"],"СТРАВИ, ЯКІ ЇДЯТЬ РУКАМИ":["Бурітос з м'ясом (400г)","Клаб бургер з котлетою (450г)","Сирний бургер (300г)","Тако з тушонкою","Тако з курячим мясом","Бургер з хрустким курячим філе в сирній ванні (300г)","Чікен Бургер з картоплею фрі (450г)","Бургер з тушеним м'ясом (420г)"],"ГАРЯЧІ ЗАКУСКИ":["Курячі крильця з соусом (1порція)","Мойва фрі (1порція)","Свинні вушка смажені з соусом (1порція)","Сирні палички гриль у лаваші (1порція)","Чіпси картопляні (1порція)","Снеки решітки (1порція)","Сир косичка та кабаноси фрі (1порція)","Куряче філе в хрусткій паніровці (1порція)","Пельмені фрі (1порція)","Курячі крильця Баффало (1порція)","Тортилья гриль","Огірки фрі","Сосиски в лаваші з гірчицею","Кульки фрі з моцарели (1порція)"],"ХЛІБ":["Булочка здобна маленька (1шт)"],"ПРОХОЛОДНІ НАПОЇ":["Аква н/г (0,5л)","Аква с/г (0,5л)","Боржомі (0,3л)","Боржомі (0,5л)","Компот ягідний (1л)","Мірінда (0,5л)","Моршинська н/г (0,33л)","Моршинська н/г (0,75л)","Моршинська с/г 0,33","Моршинська с/г (0,75л)","Пепсі (0,33л)","Пепсі (0,5л)","Ред Бул","Севен Ап (0,5л)","Тонік Евервест (0,5л)","Сік Сандора в асортименті (0,95л)"],"СОЛОДКІ СТРАВИ ТА ЩОСЬ ДО КАВИ":["Чізкейк (180г)","Шоколадний флан із морозивом (130г)","Вафельний торт з морозивом (110г)"],"СОУСИ":["Барбекю (40г)","Коктейльний (40г)","Сацебелі (40г)","Соус Бургер (40г)","Соус Сирний (40г)","Соус Соєвий (40г)","Соус Ягідний (40г)","Хрін (40г)","Часниковий (40г)","Кетчуп (40г)"]}